[
    [
        {
            "brkfst": 7.566666666666666,
            "lnch": null,
            "dnr": 17.383333333333333
        },
        {
            "brkfst": 11.866666666666667,
            "lnch": 14.233333333333333,
            "dnr": 16.783333333333335
        },
        {
            "brkfst": 6.7,
            "lnch": null,
            "dnr": null
        },
        {
            "brkfst": 6.8,
            "lnch": 12.0,
            "dnr": 17.216666666666665
        },
        {
            "brkfst": 7.366666666666666,
            "lnch": null,
            "dnr": 17.2
        },
        {
            "brkfst": null,
            "lnch": null,
            "dnr": null
        },
        {
            "brkfst": null,
            "lnch": null,
            "dnr": null
        }
    ],
    [
        {
            "brkfst": null,
            "lnch": null,
            "dnr": null
        },
        {
            "brkfst": null,
            "lnch": null,
            "dnr": null
        },
        {
            "brkfst": null,
            "lnch": null,
            "dnr": null
        },
        {
            "brkfst": null,
            "lnch": null,
            "dnr": null
        },
        {
            "brkfst": null,
            "lnch": null,
            "dnr": null
        },
        {
            "brkfst": null,
            "lnch": null,
            "dnr": null
        },
        {
            "brkfst": null,
            "lnch": null,
            "dnr": null
        }
    ],
    [
        {
            "brkfst": null,
            "lnch": null,
            "dnr": null
        },
        {
            "brkfst": null,
            "lnch": null,
            "dnr": null
        },
        {
            "brkfst": null,
            "lnch": null,
            "dnr": 16.966666666666665
        },
        {
            "brkfst": 11.983333333333333,
            "lnch": 11.983333333333333,
            "dnr": 17.166666666666668
        },
        {
            "brkfst": 8.666666666666666,
            "lnch": 15.55,
            "dnr": null
        },
        {
            "brkfst": 6.616666666666667,
            "lnch": 12.033333333333333,
            "dnr": 17.95
        },
        {
            "brkfst": 6.933333333333334,
            "lnch": null,
            "dnr": 17.483333333333334
        }
    ],
    [
        {
            "brkfst": 10.883333333333333,
            "lnch": 12.116666666666667,
            "dnr": null
        },
        {
            "brkfst": 11.666666666666666,
            "lnch": 11.666666666666666,
            "dnr": 16.916666666666668
        },
        {
            "brkfst": 6.733333333333333,
            "lnch": null,
            "dnr": 17.683333333333334
        },
        {
            "brkfst": 11.333333333333334,
            "lnch": 14.083333333333334,
            "dnr": 18.033333333333335
        },
        {
            "brkfst": 6.8,
            "lnch": 12.016666666666667,
            "dnr": 17.716666666666665
        },
        {
            "brkfst": 6.783333333333333,
            "lnch": 12.416666666666666,
            "dnr": 16.45
        },
        {
            "brkfst": 11.75,
            "lnch": 11.75,
            "dnr": null
        }
    ],
    [
        {
            "brkfst": 8.55,
            "lnch": 12.066666666666666,
            "dnr": null
        },
        {
            "brkfst": 7.45,
            "lnch": null,
            "dnr": 16.883333333333333
        },
        {
            "brkfst": 11.983333333333333,
            "lnch": 11.983333333333333,
            "dnr": 16.083333333333332
        }
    ]
]